etaf_crypto-0.1.2.dist-info/METADATA
etaf_crypto-0.1.2.dist-info/WHEEL
fate_crypto/psi/__init__.pyi
fate_crypto/psi/__init__.py
fate_crypto/__init__.py
fate_crypto/hash/__init__.pyi
fate_crypto/hash/__init__.py
fate_crypto/fate_crypto.cpython-39-powerpc64le-linux-gnu.so
etaf_crypto-0.1.2.dist-info/RECORD
